r614_config/__init__.py
r614_config/config.py
r614_config/py.typed
r614_config-0.1.7.dist-info/LICENSE
r614_config-0.1.7.dist-info/METADATA
r614_config-0.1.7.dist-info/WHEEL
r614_config-0.1.7.dist-info/RECORD
