Metadata-Version: 2.1
Name: r614-config
Version: 0.1.7
Summary: Shared config module
License: CC0 1.0
Author: Roshan Pawar
Author-email: steradian614@gmail.com
Requires-Python: >=3.11,<4.0
Classifier: License :: Other/Proprietary License
Classifier: Programming Language :: Python :: 3
Classifier: Programming Language :: Python :: 3.11
